{"stem":"1000","instances":[{"docId":"wkfm-650362","docUri":"wkfm-650362.html","score":28,"contexts":[{"form":"1000","weight":"1","pos":1475,"context":"...einge- leget kraft welchen 500 fl Heurathgutt nebst <mark>1000<\/mark> fl Widerlag auf Überleben dann jenes was wehrender Ehe...","fid":"d23e4490"},{"form":"1000","weight":"1","pos":2268,"context":"...in Copia Vidimata No 2219 eingeleget, kraft welcher <mark>1000<\/mark> fl Heurathgutt nebst 2000 fl Widerlag auf überleben,...","fid":"d23e5883"},{"form":"1000","weight":"1","pos":3602,"context":"...vidimata eingeleget, kraft welchen 500 fl Heurathsgut nebst <mark>1000<\/mark> fl Widerlag auf überleben und jenes, was wehrender Ehe...","fid":"d23e8116"},{"form":"1000","weight":"1","pos":4064,"context":"...eingeleget kraft welchen 500 fl Heu- rahtgutt nebst <mark>1000<\/mark> fl Widerlag auf Überleben, dann jenes, was wehren...","fid":"d23e8822"},{"form":"1000","weight":"1","pos":5276,"context":"...Heurathscontract No 2225 in Copia vidimata eingeleget kraft welchen <mark>1000<\/mark> fl heurathsgutt nebst 2000 fl Widerlag 0 auf Überleben...","fid":"d23e10397"},{"form":"1000","weight":"1","pos":5576,"context":"..., kraft welchen 500 fl Heu- rathgutt nebst <mark>1000<\/mark> fl Widerlag auf Uberleben, dann jenes, was wehrender...","fid":"d23e11045"},{"form":"1000","weight":"1","pos":5825,"context":"...No 2229 in Copia vidimata eingeleget, kraft welchen <mark>1000<\/mark> fl heurathgutt nebst 2000 fl Widerlag auf Überleben,...","fid":"d23e11485"},{"form":"1000","weight":"1","pos":5926,"context":"...No 223 in Copia vidimata angeleget, kraft welchen <mark>1000<\/mark> fl Heurathgutt nebst 2000 fl Widerlag auf Überleben,...","fid":"d23e11651"},{"form":"1000","weight":"1","pos":6062,"context":"...vidimata eingeleget, kraft welchen 500 fl Heurathgutt nebst <mark>1000<\/mark> fl Widerlag auf Uberl wie auch alle Haus Ein-...","fid":"d23e11860"},{"form":"1000","weight":"1","pos":6524,"context":"..., kraft welchen 500 fl Heu- rathgut nebst <mark>1000<\/mark> fl Widerlag auf Überleben, jenes anbey was wehrender...","fid":"d23e12583"},{"form":"1000","weight":"1","pos":6609,"context":"...No 2242 in Copia vidimata eingelegt, kraft welchen <mark>1000<\/mark> fl Heurathsgutt nebst 2000 fl Widerlag auf Überleben jenes...","fid":"d23e12722"},{"form":"1000","weight":"1","pos":7127,"context":"...No 2240 in Cipia vidimata eingeleget, kraft welchen <mark>1000<\/mark> fl Heurathgutt nebst 2000 fl Wider- lag wie...","fid":"d23e13438"},{"form":"1000","weight":"1","pos":7303,"context":"...seiner Mutter, wie selbe zur zweyten Ehe geschritten <mark>1000<\/mark> fl an intee hievon auf 12 Jahr 600 fl...","fid":"d23e13639"},{"form":"1000","weight":"1","pos":7314,"context":"...fl an Schwesterlichen Erbtheil 1050 fl von seiner Mutter <mark>1000<\/mark> fl Sa 9050 fl","fid":"d23e13639"},{"form":"1000","weight":"1","pos":8512,"context":"...Schwiger Mutter Maria Magdalena Mayerhoferin pr 500 fl zusamen <mark>1000<\/mark> fl zusamen Eigenthum 1350 fl zu Completirung des übrigen...","fid":"d23e15561"},{"form":"1000","weight":"1","pos":8654,"context":"...Aprilis 752 errichteten Heuraths Contract ein- geleget: worinnen <mark>1000<\/mark> Heurathguth 2000 fl Widerlag, und das beederseitige sowohl...","fid":"d23e15856"},{"form":"1000","weight":"1","pos":8776,"context":"...nebst den handlungs Gerechtigkeit alß heuraths gut wie auch <mark>1000<\/mark> Widerlag auf überleben pact je anbey jenes jenes was...","fid":"d23e16036"},{"form":"1000","weight":"1","pos":8830,"context":"...Contract Anmerckungen eingeleget, worinnen Heurathguth 500 fl Widerlag <mark>1000<\/mark> fl und das erwerbende Vermögen ein gleiches Guth contrahiret...","fid":"d23e16036"},{"form":"1000","weight":"1","pos":8964,"context":"...mit der Francisca  Rathgebin tract eingelegt, worinnen Heurathguth <mark>1000<\/mark> fl Widerlaag 2000 fl 100 Species Cermnizer Ducaten zu...","fid":"d23e16326"},{"form":"1000","weight":"1","pos":9209,"context":"...Heurath-Guth 500 fl Widerlaag samt Handlungs Gerichtigkeit <mark>1000<\/mark> fl und das wehrender Ehe erwerbend- und er-...","fid":"d23e16649"},{"form":"1000","weight":"1","pos":9913,"context":"...- mus nro 2247 worinnen Heurath 500 fl Widerlaag <mark>1000<\/mark> fl Parapher- num 1000 fl und was beede...","fid":"d23e17792"},{"form":"1000","weight":"1","pos":9916,"context":"...Heurath 500 fl Widerlaag 1000 fl Parapher- num <mark>1000<\/mark> fl und was beede wehrend ihrer Ehe erwerben und...","fid":"d23e17792"},{"form":"1000","weight":"1","pos":9988,"context":"...: 753 No 1788 et 1789 in Copiis vidimatis <mark>1000<\/mark> fl an einer Kupfer-Amtsobligation ddto 6ten...","fid":"d23e17841"},{"form":"1000","weight":"1","pos":10085,"context":"...Marty errichteten Heuraths-Contract eingeleget, worinnen Heurathguth <mark>1000<\/mark> fl Widerlag samet 2000 fl samt seiner Handlung,...","fid":"d23e18057"},{"form":"1000","weight":"1","pos":10101,"context":"...Worunter quittiret ist, das er das Heurath Guth pr <mark>1000<\/mark> fl untern 8ten Marty 758 baar empfangen habe....","fid":"d23e18057"},{"form":"1000","weight":"1","pos":10167,"context":"...24ten Septembris 751 errichteten Heuraths Contract dd to <mark>1000<\/mark> fl, das erwerbend und ererbende Vermögen ein gleiches Guth...","fid":"d23e18185"},{"form":"1000","weight":"1","pos":10365,"context":"...errichteten Heuraths Con- tract eingelegt, worinnen Heurath <mark>1000<\/mark> fl Widerlag 2000 fl zu einer Morgengaab die Markt...","fid":"d23e18452"},{"form":"1000","weight":"1","pos":10374,"context":"...-Hütten von der Brauth, eine Donation pr <mark>1000<\/mark> fl von dem Brauthigam seiner Brauth samt allen Nottwendigkeiten...","fid":"d23e18452"}]},{"docId":"wkfm-560230","docUri":"wkfm-560230.html","score":24,"contexts":[{"form":"1000","weight":"1","pos":3549,"context":"...No 2103 errichteten Copia vidimata eingeleget, krafft welchen <mark>1000<\/mark> fl Heurathsgutt nebst 2000 fl Wider lag dergestalten auf...","fid":"d10e8759"},{"form":"1000","weight":"1","pos":6024,"context":"...vidimata eingeleget, krafft welchen 500 fl Heurathgutt nebst <mark>1000<\/mark> fl Widerlag auf Überleben jenes anbey, was wehrender...","fid":"d10e12996"},{"form":"1000","weight":"1","pos":6429,"context":"..., kraft welchen 500 fl heuratgutt, so mit <mark>1000<\/mark> fl. widerleget worden auf überleben, jenes anbey weh...","fid":"d10e13661"},{"form":"1000","weight":"1","pos":6477,"context":"...No 2101 in Copia vidimata eingelegt, krafft welchen <mark>1000<\/mark> fl heurathsgutt nebst 2000 fl Widerlag auf Uberleben,...","fid":"d10e13661"},{"form":"1000","weight":"1","pos":6777,"context":"...einge- leget krafft welchen 500 fl heurathgutt nebst <mark>1000<\/mark> fl Widerlag auf Überleben, dann so was wehrender...","fid":"d10e14227"},{"form":"1000","weight":"1","pos":7116,"context":"...leget krafft welchen 500 fl Gulden Heurath gutt nebst <mark>1000<\/mark> fl Widerlag auf Uberleben anbey, was wehrender Ehe...","fid":"d10e14717"},{"form":"1000","weight":"1","pos":7528,"context":"...vidimata eingelegt, krafft welchen 500 fl heurathgutt nebst <mark>1000<\/mark> fl Widerlag auf überleben anbey jenes, was wehrender Ehe...","fid":"d10e15240"},{"form":"1000","weight":"1","pos":7640,"context":"...Zahler Constituiret in anbey dem nächsten von Haus etliche <mark>1000<\/mark> fl erwarthe, alß verhoffe er seinen fundum ausgewiesen...","fid":"d10e15378"},{"form":"1000","weight":"1","pos":7702,"context":"...eingleget, krafft welchen 500 fl heurath Gutt nebst <mark>1000<\/mark> fl Widerlag auf Überleben pactiret anbey vorgesehen worden, daß...","fid":"d10e15486"},{"form":"1000","weight":"1","pos":7746,"context":"...Leibs erben und testament versterben würde dem Uberlebenden besa <mark>1000<\/mark> zufallen sollen. Anmerckungen","fid":"d10e15486"},{"form":"1000","weight":"1","pos":8110,"context":"...No 2087 in Copia vidimata eingeleget, krafft welchen <mark>1000<\/mark> fl heurath Gutt nebst 1000 fl Widerlag auf Überleben...","fid":"d10e16074"},{"form":"1000","weight":"1","pos":8114,"context":"...eingeleget, krafft welchen 1000 fl heurath Gutt nebst <mark>1000<\/mark> fl Widerlag auf Überleben, anbey sowohl das gegenwärtige...","fid":"d10e16074"},{"form":"1000","weight":"1","pos":8312,"context":"...No 2079 in copia vidimata eingeleget, krafft welchen <mark>1000<\/mark> fl Widerlag Heurathsgutt nebst 2000 fl Widerlag auf Überleben...","fid":"d10e16374"},{"form":"1000","weight":"1","pos":9175,"context":"...No 2095 in Copia vidimata eingeleget, kraft welchen <mark>1000<\/mark> fl heurathgutt nebst 2000 fl Widerlag auf Überleben samt...","fid":"d10e17781"},{"form":"1000","weight":"1","pos":9966,"context":"...vidimata eingleget krafft welchen 500 fl heuraths gutt nebst <mark>1000<\/mark> fl Widerlag nebst denen Mobilien und Hausrath in casum...","fid":"d10e19026"},{"form":"1000","weight":"1","pos":11052,"context":"...eingeleget, krafft welchen 500 fl Heurath Gutt sowie <mark>1000<\/mark> fl Widerlag und alle Einmahlig und künftige Einrichtung fahrung...","fid":"d10e20752"},{"form":"1000","weight":"1","pos":11158,"context":"...Heurath Contract eingleget, worinnen Heurathguth 500 fl Widerlag <mark>1000<\/mark> fl und das erwerbende Vermögen ein gleiches Gut stipuliret...","fid":"d10e20907"},{"form":"1000","weight":"1","pos":11370,"context":"...Heuraths Contract eingeleget, wo- rinnen Heurathguth 500 Widerlag <mark>1000<\/mark> fl und von der Brauthigam der Brauth zu einem...","fid":"d10e21143"},{"form":"1000","weight":"1","pos":11640,"context":"...2000 fl und 4ten 7br: d. a. pr <mark>1000<\/mark> fl No 1244 et 1245 dann einen Wechsel-...","fid":"d10e21459"},{"form":"1000","weight":"1","pos":11701,"context":"...in orig: No 2112 geleget, krafft welchen <mark>1000<\/mark> fl heurathgutt samt 2000 fl Widerlag auf überleben,...","fid":"d10e21704"},{"form":"1000","weight":"1","pos":11897,"context":"...No 2115 eingeleget krafft welchen die Braut dem Bräutigam <mark>1000<\/mark> fl nebst der Handlung mit allen Recht und Gerechtigkeiten...","fid":"d10e21977"},{"form":"1000","weight":"1","pos":12377,"context":"...in orig: No 2109 eingeleget, kraft welchen <mark>1000<\/mark> fl Heurathgutt samt 2000 fl Widerlag auf überleben und...","fid":"d10e22723"},{"form":"1000","weight":"1","pos":12613,"context":"...Contract in orig: No 2111 eingeleget kraft welchen <mark>1000<\/mark> fl Heurath Gutt und 2000 fl Widerlag dann daß...","fid":"d10e23176"},{"form":"1000","weight":"1","pos":12980,"context":"...ausschlag ddto 6ten 754 in Abschrifft No 1271 <mark>1000<\/mark> fl An hievon abgefahlenen Intee und erspahrten solario laut...","fid":"d10e23775"}]},{"docId":"wkfm-560252","docUri":"wkfm-560252.html","score":15,"contexts":[{"form":"1000","weight":"1","pos":2969,"context":"...- schlossenen Heurathscontract dd too 2124 eingeleget krafft welchen <mark>1000<\/mark> fl Heurathgutt und 2000 fl nebst der Handlung und...","fid":"d11e6924"},{"form":"1000","weight":"1","pos":3632,"context":"...vidimata eingeleget, kraft welchen 500 fl Heurathgutt mit <mark>1000<\/mark> fl Widerlag auf Überleben und was wehrender Ehe erworben...","fid":"d11e8108"},{"form":"1000","weight":"1","pos":3804,"context":"...750 errichteten Heuraths Contract eingeleget, worinnen das Heurathguth <mark>1000<\/mark> fl die Wiederlag 2000 fl und das künftig erwerbend...","fid":"d11e8406"},{"form":"1000","weight":"1","pos":4073,"context":"...2116 eingeleget krafft welchen 500 fl Heurathgutt wide nebst <mark>1000<\/mark> fl Widerlag auf überleben und was wehrender Ehe erworben...","fid":"d11e8728"},{"form":"1000","weight":"1","pos":4165,"context":"...ddto 9ten Febr: 738 No 1295 pr <mark>1000<\/mark> fl ausgewisen in Summa Sa pr 4047 fl 34...","fid":"d11e8862"},{"form":"1000","weight":"1","pos":4446,"context":"...2122 eingeleget krafft welchen 500 fl Heurath Gutt nebst <mark>1000<\/mark> fl widerlag auf überleben dann was wehrender Ehe erworben...","fid":"d11e9371"},{"form":"1000","weight":"1","pos":4809,"context":"...selber als Eigenthumlich ansezet Eine Ehrenhafter: obligation pr <mark>1000<\/mark> fl Wagnerischen Wechselbrief pr 1500 fl det: Kofler...","fid":"d11e9926"},{"form":"1000","weight":"1","pos":5315,"context":"...: von  Radlio  pr 1200 fl an erspahrten salario <mark>1000<\/mark> fl Sa 8107 fl 45 xr zu wessen bekräfftigung...","fid":"d11e10775"},{"form":"1000","weight":"1","pos":5328,"context":"...das er Chiocino bey ihm Cescotti an erspahrten solario <mark>1000<\/mark> fl stehen habe ddto 22ten Apr: 743...","fid":"d11e10775"},{"form":"1000","weight":"1","pos":5906,"context":"...die obligation ddto 13 Febr: 730 haftet pr <mark>1000<\/mark> fl auf der obligation ddto 30ten Apr:...","fid":"d11e11754"},{"form":"1000","weight":"1","pos":5943,"context":"...18ten Apr: 748 No 1321 eingeleget pr <mark>1000<\/mark> fl Sa 4000 fl","fid":"d11e11754"},{"form":"1000","weight":"1","pos":5968,"context":"...richteten Heuraths Contract eingelegt, worinnen Heurath- guth <mark>1000<\/mark> fl. Widerlag 2000 fl. stipuliret sind: Anmerckungen","fid":"d11e11989"},{"form":"1000","weight":"1","pos":6306,"context":"...Contract No 2126 in orig: eingeleget krafft welchen <mark>1000<\/mark> fl Heurathsgutt nebst 2000 fl Widerlag auf überleben stipuliret...","fid":"d11e12557"},{"form":"1000","weight":"1","pos":6730,"context":"...krafft welchen Heurathgutt pr 800 fl nebst widerlag pr <mark>1000<\/mark> fl auf überleben, dann jenes was wehrender Ehe...","fid":"d11e13126"},{"form":"1000","weight":"1","pos":6930,"context":"...Contract No 2127 in orig: eingeleget kraft welchen <mark>1000<\/mark> heurath- gutt mit 2000 fl Widerlag 0 auf...","fid":"d11e13634"}]},{"docId":"wkfm-650361","docUri":"wkfm-650361.html","score":14,"contexts":[{"form":"1000","weight":"1","pos":779,"context":"...Copia vidimata eingeleget kraft welchen 500 fl Heurathgutt nebst <mark>1000<\/mark> fl Widerlag auf Überleben, dann jenes was wehrender...","fid":"d22e2259"},{"form":"1000","weight":"1","pos":2116,"context":"...er in Unglüksfall wegen denen von seinem Sohn pactirten <mark>1000<\/mark> fl heurathsgutt und 2000 fl Widerlag respectu 1500 fl...","fid":"d22e4616"},{"form":"1000","weight":"1","pos":2157,"context":"...Heurathscontract No 2204 in Copia vidimata eingeleget kraft welchen <mark>1000<\/mark> fl Heurathgutt nebst 2000 fl Widerlag auf überleben,...","fid":"d22e4714"},{"form":"1000","weight":"1","pos":2170,"context":"...als ein gleiches gutt und das die Braut jene <mark>1000<\/mark> fl welche sie neb nebst der Einrichtung von ihren...","fid":"d22e4714"},{"form":"1000","weight":"1","pos":2591,"context":"...743 No 2213 in vidimata copia eingeleget kraft welchen <mark>1000<\/mark> fl Widerlag Heurathgutt nebst 2000 fl Widerlag auf Über-...","fid":"d22e5314"},{"form":"1000","weight":"1","pos":2639,"context":"...Braut von ihrer Großmutter Cuni-gunda Weygertin mitgegebene <mark>1000<\/mark> fl der dem Brautigam zur Nuznußung der Braut aber...","fid":"d22e5314"},{"form":"1000","weight":"1","pos":3057,"context":"...in Copia vidimata No 2209 eingeleget, kraft welchen <mark>1000<\/mark> fl heurathgut nebst 2000 fl Widerlag auf uberleben da...","fid":"d22e6119"},{"form":"1000","weight":"1","pos":3215,"context":"...25ten Janu: 742 in Cap: pr <mark>1000<\/mark> fl und 3 Jährigen intee pr 150 fl zusamen...","fid":"d22e6373"},{"form":"1000","weight":"1","pos":3651,"context":"...vidimata eingeleget kraft welchen 500 fl Heurath gutt nebst <mark>1000<\/mark> fl Widerlag auf überleben wie auch die samentliche Haus...","fid":"d22e7026"},{"form":"1000","weight":"1","pos":3673,"context":"...wann Kinder vorhanden mit 2000 fl ansonsten aber mit <mark>1000<\/mark> fl aus des Bräutigams Vermögen zu diponiren befugt seyn...","fid":"d22e7026"},{"form":"1000","weight":"1","pos":3919,"context":"...Kinder vorhanden der uberlebende Theil den befreunden des verstorbenen <mark>1000<\/mark> fl hinausgeben solle, pactiret worden Anmerckungen","fid":"d22e7524"},{"form":"1000","weight":"1","pos":3988,"context":"...14ten Martii 74 No 1094 in Cap: <mark>1000<\/mark> fl und sechsjährigen intee a 6 pCto 390 fl...","fid":"d22e7599"},{"form":"1000","weight":"1","pos":4074,"context":"...und burgerlichen Gewerb zugebrachte zum Heuraths Gutt zugebracht, <mark>1000<\/mark> fl samt 2000 fl Widerlag auf uberleben, dann...","fid":"d22e7811"},{"form":"1000","weight":"1","pos":4673,"context":"...pr wovon Copia vidimata No 1685 et 1686 pr <mark>1000<\/mark> fl zusamen 2000 fl an interessen hervon 20 fl...","fid":"d22e8616"}]},{"docId":"wkfm-560296","docUri":"wkfm-560296.html","score":14,"contexts":[{"form":"1000","weight":"1","pos":1636,"context":"...No 2151 eingeleget kraft welchen 500 fl Heurathgutt nebst <mark>1000<\/mark> fl Widerlag auf Uberleben dann das xxx weh-...","fid":"d14e4207"},{"form":"1000","weight":"1","pos":1917,"context":"...2141 eingeleget kraft welchen 500 fl Heurath Gutt nebst <mark>1000<\/mark> fl Widerlag auf Uberleben und jenes was wehrender Ehe...","fid":"d14e4668"},{"form":"1000","weight":"1","pos":2084,"context":"...Vidimata No 2147 einge leget kraft welchen <mark>1000<\/mark> fl Heurath Gutt nebst 2000 fl Widerlag auf über-...","fid":"d14e4915"},{"form":"1000","weight":"1","pos":2542,"context":"...vidimata eingeleget kraft welchen 500 fl Heurath Gutt nebst <mark>1000<\/mark> fl Widerlag auf überleben, und jenes was wehrender...","fid":"d14e5728"},{"form":"1000","weight":"1","pos":3144,"context":"...in Copia vidimata No 214 eingeleget, kraft welchen <mark>1000<\/mark> fl Heurat Gutt und 2000 fl Widerlag nebst deren...","fid":"d14e6417"},{"form":"1000","weight":"1","pos":3182,"context":"...vorhanden mit 2000 fl falß aber keine vorhanden mit <mark>1000<\/mark> fl zu dispariren befugt seye solle. Mitls Anbringen...","fid":"d14e6417"},{"form":"1000","weight":"1","pos":3210,"context":"...No 2105 in Copia vidimata eingeleget, kraft welchen <mark>1000<\/mark> fl Heurat Gutt dann nebst 2000 fl Widerlag dann...","fid":"d14e6417"},{"form":"1000","weight":"1","pos":3592,"context":"...welchen 500 fl Heur[aths] Gutt nebst <mark>1000<\/mark> fl Widerlag auf überleben, das und das wehrender...","fid":"d14e7413"},{"form":"1000","weight":"1","pos":3807,"context":"...geschlossenen Heuraths Contract No 2153 eingeleget, kraft welchen <mark>1000<\/mark> fl Heurath Gutt und 2000 fl Wider- lag...","fid":"d14e7772"},{"form":"1000","weight":"1","pos":4378,"context":"...in Copia vidimata No 2157 eingeleget, Kraft welchen <mark>1000<\/mark> fl Heurath Gutt nebst 2000 fl Widerlag auf überleben...","fid":"d14e8859"},{"form":"1000","weight":"1","pos":5525,"context":"...3000 fl Heurat Gutt und 3000 fl Widerlag nebst <mark>1000<\/mark> fl Morgen=Gaab dergestalt stipuliret worden, daß falß der...","fid":"d14e10575"},{"form":"1000","weight":"1","pos":5540,"context":"...der Heurat Gutts pr 3000 fl und Morgengaab pr <mark>1000<\/mark> fl andern 5000 fl nebst der völligen Einricht an...","fid":"d14e10575"},{"form":"1000","weight":"1","pos":5568,"context":"...Heurath Gutt pr 3000 fl nebst der Morgengab pr <mark>1000<\/mark> fl, wann die Braut mit solcher nicht anderst dispariren...","fid":"d14e10575"},{"form":"1000","weight":"1","pos":5881,"context":"...: 753 pr 133fl an baaren und Effecten <mark>1000<\/mark> fl Sa 8835 fl 44 1\/2 xr ","fid":"d14e11322"}]},{"docId":"wkfm-650348","docUri":"wkfm-650348.html","score":14,"contexts":[{"form":"1000","weight":"1","pos":1413,"context":"...in Copia vidimata No 2167 eingeleget, kraft welchen <mark>1000<\/mark> fl heurathgutt auf überleben, dann daß die Braut...","fid":"d17e3527"},{"form":"1000","weight":"1","pos":3296,"context":"...Anbringen de ps: 7ten Janu: 738 No <mark>1000<\/mark> hat der Heß die obigen Schklers wehrend seiner ab-...","fid":"d17e6690"},{"form":"1000","weight":"1","pos":4250,"context":"...No 2169 in orig: eingeleget, krafft welchen <mark>1000<\/mark> fl heuraths- gutt nebst 2000 fl Widerlag auf...","fid":"d17e8228"},{"form":"1000","weight":"1","pos":4438,"context":"...2171 eingeleget, kraft welchen 500 fl heurathgutt nebst <mark>1000<\/mark> fl Widerlag und denen Haus Effecten und Einrichtung auf...","fid":"d17e8622"},{"form":"1000","weight":"1","pos":4656,"context":"...dem ihrigen zur Sicherheit denen Creditoren gewidmet haben wolle <mark>1000<\/mark> fl dann hat der Johann Georg Grindtler das orig...","fid":"d17e8933"},{"form":"1000","weight":"1","pos":4935,"context":"...Julij 747 verrichteten Heuraths Contract eingeleget, worinnen Heurath <mark>1000<\/mark> fl und 2000 fl Widerlag auf überlebe, paraphernal...","fid":"d17e9188"},{"form":"1000","weight":"1","pos":5475,"context":"...Heurathscontract in orig: No 2175 eingeleget kraft welchen <mark>1000<\/mark> fl Heurathgutt nebst 2000 fl Wider- lag auf...","fid":"d17e9956"},{"form":"1000","weight":"1","pos":5762,"context":"...No 2179 in orig: eingeleget, kraft welchen <mark>1000<\/mark> fl heu- rathgutt nebst 2000 fl Widerlag auf...","fid":"d17e10357"},{"form":"1000","weight":"1","pos":6005,"context":"...zufallen, keiner aus beyden be- sondere Negotien bey <mark>1000<\/mark> fl Pönn od für die armen fr machen, fremte...","fid":"d17e10617"},{"form":"1000","weight":"1","pos":6235,"context":"...No 2177 eingeleget kraft welchen 500 fl heurathgutt nebst <mark>1000<\/mark> fl Widerlag auf überleben, dann jenes was wehrender...","fid":"d17e11007"},{"form":"1000","weight":"1","pos":6301,"context":"...in Copia vidimata eingelegten Wechslbriefen pr 2000 fl und <mark>1000<\/mark> fl zusamen 3000 fl an einen det: von...","fid":"d17e11068"},{"form":"1000","weight":"1","pos":6316,"context":"...No 1532 pr 1200 fl an baaren pr Cassa <mark>1000<\/mark> fl zusamen Eigenthumlich 5200 fl zu Completirung des uberreste...","fid":"d17e11068"},{"form":"1000","weight":"1","pos":6373,"context":"...: eingeleget, kraft welchen 500 fl Heurathgutt nebst <mark>1000<\/mark> fl Widerlag auf über- leben, dann jenes was...","fid":"d17e11216"},{"form":"1000","weight":"1","pos":6616,"context":"...orig: Heuraths Contract No 2182 eingeleget kraft welchen <mark>1000<\/mark> fl Heurath nebst 2000 fl Widerlag auf überleben,...","fid":"d17e11631"}]},{"docId":"wkfm-560275","docUri":"wkfm-560275.html","score":10,"contexts":[{"form":"1000","weight":"1","pos":2531,"context":"...vidimato No 2135 einge- leget, krafft welchen <mark>1000<\/mark> 500 fl heurathsgutt nebst 1500 fl Widerlag auf nebst...","fid":"d12e5284"},{"form":"1000","weight":"1","pos":2567,"context":"...wann Kinder vorhanden 2000 fl wann aber keine vorhanden <mark>1000<\/mark> fl zu leztwilliger disposition aus des Bräutigam Vermögen zufallen...","fid":"d12e5284"},{"form":"1000","weight":"1","pos":2788,"context":"...heurathscontract N in vidimus No 2129 eingeleget krafft welchen <mark>1000<\/mark> fl heurathgutt nebst 2000 fl Widerlag auf überleben und...","fid":"d12e5750"},{"form":"1000","weight":"1","pos":3031,"context":"...ihrem ehewirthen zugebracht zur Sicherheit deren Creditoren hafften sollen <mark>1000<\/mark> fl Sa 4412 fl 47 1\/2 xr ","fid":"d12e6206"},{"form":"1000","weight":"1","pos":3529,"context":"...in copia vidimata No 2133 eingeleget, krafft welchen <mark>1000<\/mark> fl heurathgutt nebst 2000 fl Widerlag auf überleben,...","fid":"d12e7048"},{"form":"1000","weight":"1","pos":3728,"context":"...Mayr und Hölzl ddto 27ten May 744 pr <mark>1000<\/mark> fl zwey Stat Banco obligationen jede pr 300 fl...","fid":"d12e7366"},{"form":"1000","weight":"1","pos":3824,"context":"...Heuraths Contract eingeleget, worinnen 500 fl Heurathgut, <mark>1000<\/mark> fl Wi- derlag und zu einem Hochzeit praesent für...","fid":"d12e7637"},{"form":"1000","weight":"1","pos":4001,"context":"...xr an zwey Wechselbriefen jeden pr 500 fl zusamen <mark>1000<\/mark> fl an einer vicedomlichen Vicedom: obligation oblig:...","fid":"d12e7796"},{"form":"1000","weight":"1","pos":4327,"context":"...Schwarzleüthner und Sohn ddto Xbr: 753 No 1386 <mark>1000<\/mark> fl an prationen Mobilien und Effecten und avociirten in...","fid":"d12e8253"},{"form":"1000","weight":"1","pos":4334,"context":"...Mobilien und Effecten und avociirten in der Straussischen Handlung <mark>1000<\/mark> fl Sa Eigenthum 6000 fl Zu Completirung der übrigen...","fid":"d12e8253"}]},{"docId":"wkfm-560280","docUri":"wkfm-560280.html","score":6,"contexts":[{"form":"1000","weight":"1","pos":948,"context":"...schuldig seye er, der Egg[er] dem Babitsch <mark>1000<\/mark> fl an Waaren und 1000 fl an activis,...","fid":"d13e1714"},{"form":"1000","weight":"1","pos":950,"context":"...Egg[er] dem Babitsch 1000 fl an Waaren und <mark>1000<\/mark> fl an activis, und 500 fl in baaren...","fid":"d13e1714"},{"form":"1000","weight":"1","pos":963,"context":"...Fest nebst einigen alten Einrichtung herausgeben, dann jene <mark>1000<\/mark> fl welche der Babitsch wehrender Societaet denen PP Carmelitern...","fid":"d13e1714"},{"form":"1000","weight":"1","pos":1030,"context":"...in Copia vidimata No 2107 eingeleget, kraft welchen <mark>1000<\/mark> fl Heurath Gut nebst 2000 fl Widerlag auf Überleben...","fid":"d13e2198"},{"form":"1000","weight":"1","pos":1347,"context":"...eingeleget, kraft welchen 800 fl Heurath Gutt einlegt <mark>1000<\/mark> fl Widerlag alß ein auf Überleben dann jenes, was...","fid":"d13e2648"},{"form":"1000","weight":"1","pos":1413,"context":"...fl Wiederlag 200 fl Paraphernalia\/Paraphernalien Parapher: <mark>1000<\/mark> fl Stipulirt sind. Solcher lieget den alt protocolirten Heuraths...","fid":"d13e2765"}]},{"docId":"wkfm-650350","docUri":"wkfm-650350.html","score":6,"contexts":[{"form":"1000","weight":"1","pos":615,"context":"...Contract Anmerckungen 0 ständige entschiden werden und jeder bey <mark>1000<\/mark> fl Pöen in ein und andern fall bey der...","fid":"d18e1605"},{"form":"1000","weight":"1","pos":1881,"context":"...No 2188 in Copia vidimata eingeleget, krafft welchen <mark>1000<\/mark> fl heurath gutt nebst 2000 fl Widerlag auf überleben...","fid":"d18e3857"},{"form":"1000","weight":"1","pos":2385,"context":"...No 2190 eingeleget kraft welchen 500 fl heuratgut nebst <mark>1000<\/mark> fl Widerlag auf uberleben, dann jenes was wehrender...","fid":"d18e4711"},{"form":"1000","weight":"1","pos":2640,"context":"...2192 eingeleget, krafft welchen 500 fl heurathgutt nebst <mark>1000<\/mark> fl Widerlag auf Uberleben, dann jeines was wehrender...","fid":"d18e5160"},{"form":"1000","weight":"1","pos":2811,"context":"...eingleget, kraft welchen 500 fl heurath gutt nebst <mark>1000<\/mark> fl Wider- lag auf überleben, dann jenen,...","fid":"d18e5397"},{"form":"1000","weight":"1","pos":3158,"context":"...No 2194 in orig: eingeleget, kraft welchen <mark>1000<\/mark> fl Heurathgutt nebst 2000 fl Widerlag auf überleben,...","fid":"d18e5769"}]},{"docId":"wkfm-650351","docUri":"wkfm-650351.html","score":6,"contexts":[{"form":"1000","weight":"1","pos":2306,"context":"...Zwistigkeiten nicht anderst als von zwey Handlungs Verständigen bey <mark>1000<\/mark> Reichstaler Rth : Straf zur burgerlad ausgemachet werden sollen...","fid":"d19e4867"},{"form":"1000","weight":"1","pos":2472,"context":"...8br: 768 einge- leget, worinnen Heurath guth <mark>1000<\/mark>, Wiederlag 2000 fl Morgen- gab 50 Species #,...","fid":"d19e5209"},{"form":"1000","weight":"1","pos":4075,"context":"...Contract ein geleget, worinnen heurath 500 fl Widerlag <mark>1000<\/mark> somit dann mit 6 paar silber Messer Gabl und...","fid":"d19e7686"},{"form":"1000","weight":"1","pos":4272,"context":"...500 fl samt der Haus Einrichtung als Heurathgutt nebst <mark>1000<\/mark> fl Widerlag auf uberleben, das wehrender Ehe erwerben...","fid":"d19e7988"},{"form":"1000","weight":"1","pos":4473,"context":"...Anmerckungen 0 zwey verständige entschiden werden, und jeder bey <mark>1000<\/mark> fl Pönn zu aquiesciren schuldig seye","fid":"d19e8135"},{"form":"1000","weight":"1","pos":4714,"context":"...nro: 2201 eingelegt, worinnen Heurathguth 500 Widerlaag <mark>1000<\/mark> fl und das wehrender Ehe erwerbend und ererbende Vermögen...","fid":"d19e8636"}]},{"docId":"wkfm-564767","docUri":"wkfm-564767.html","score":4,"contexts":[{"form":"1000","weight":"1","pos":2080,"context":"...in Copia vidimata No 2161 eingeleget, krafft welchen <mark>1000<\/mark> fl heur- rath Gutt nebst 2000 fl Widerlag...","fid":"d15e4657"},{"form":"1000","weight":"1","pos":2683,"context":"...eingeleget, krafft welchen 500 fl heurath gutt nebst <mark>1000<\/mark> fl Widerlag auf überleben, dann jenes, was wehrenden...","fid":"d15e5635"},{"form":"1000","weight":"1","pos":2942,"context":"...orig: eingeleget krafft welchen 500 fl heurathgutt nebst <mark>1000<\/mark> fl Wider- lag auf überleben, dann jenes,...","fid":"d15e6158"},{"form":"1000","weight":"1","pos":3063,"context":"...4ten 7br: 753 No 232 eingeleget krafft welchen <mark>1000<\/mark> fl heurath Gutt nebst 2000 fl Widerlag auf überleben...","fid":"d15e6329"}]},{"docId":"wkfm-560225","docUri":"wkfm-560225.html","score":4,"contexts":[{"form":"1000","weight":"1","pos":1279,"context":"...No 2975 eingeleget krafft welchen 500 fl Heurathgutt und <mark>1000<\/mark> fl Widerlag auf überleben stipuliret, die Braut dem...","fid":"d8e2777"},{"form":"1000","weight":"1","pos":1285,"context":"...Widerlag auf überleben stipuliret, die Braut dem Bräutigam <mark>1000<\/mark> fl der- gestalten 1000 fl eigenthumblich uberlasset, daß...","fid":"d8e2777"},{"form":"1000","weight":"1","pos":1287,"context":"..., die Braut dem Bräutigam 1000 fl der- gestalten <mark>1000<\/mark> fl eigenthumblich uberlasset, daß ihr solche falß er...","fid":"d8e2777"},{"form":"1000","weight":"1","pos":1469,"context":"...Contract eingele- get, worinnen 500 fl Heurathguth <mark>1000<\/mark> fl Widerlag, das übrige der Brauth Vermögen als...","fid":"d8e3171"}]},{"docId":"wkfm-650384","docUri":"wkfm-650384.html","score":4,"contexts":[{"form":"1000","weight":"1","pos":2669,"context":"...No 2243 in Copia vidimata eingeleget, kraft welchen <mark>1000<\/mark> fl heurathgutt nebst 2000 fl Widerlag auf Überleben,...","fid":"d25e5811"},{"form":"1000","weight":"1","pos":2809,"context":"...Copia vidimata eingeleget kraft welchen 500 fl Heurathgutt nebst <mark>1000<\/mark> fl Widerlag auf Überleben dann jenes, was wehrender Ehe...","fid":"d25e6013"},{"form":"1000","weight":"1","pos":3156,"context":"...Copia vidimata eingeleget, kraft welchen 500 Heurathgutt nebst <mark>1000<\/mark> fl Widerlag dann die Einrichtung in Casum intestati auf...","fid":"d25e6473"},{"form":"1000","weight":"1","pos":3317,"context":"...eingeleget, kraft welchen 500 fl heurath Gutt nebst <mark>1000<\/mark> fl Widerlag auf Überleben und zur Sicherheit dessen die...","fid":"d25e6729"}]},{"docId":"wkfm-650354","docUri":"wkfm-650354.html","score":4,"contexts":[{"form":"1000","weight":"1","pos":754,"context":"...zweyen oder allenfals dreyen verständigen entschiden und dabey bey <mark>1000<\/mark> Straf zur disposition des St. Johann Joanis Nepo:-...","fid":"d20e1558"},{"form":"1000","weight":"1","pos":849,"context":"...No 2200 in orig: eingeleget, kraft welchen <mark>1000<\/mark> fl heurath Gutt nebst 2000 fl Widerlag auf überleben...","fid":"d20e1777"},{"form":"1000","weight":"1","pos":930,"context":"...No 2202 in copia vidimata eingeleget, kraft welchem <mark>1000<\/mark> fl heurath- Gutt nebst 2000 fl Widerlag dergestalten...","fid":"d20e1910"},{"form":"1000","weight":"1","pos":1203,"context":"...ddto 27ten 7br: 752 No 1657 eingeleget pr <mark>1000<\/mark> fl Sa 8000 fl","fid":"d20e2335"}]},{"docId":"wkfm-650377","docUri":"wkfm-650377.html","score":3,"contexts":[{"form":"1000","weight":"1","pos":761,"context":"...in Cipia vidimata No 2186 eingeleget, kraft welchen <mark>1000<\/mark> fl heuraths gutt nebst 2000 fl Widerlag auf Überleben...","fid":"d24e1707"},{"form":"1000","weight":"1","pos":871,"context":"...Ehewirthen vermög heuraths Contract geschänket und wirklich behändiget habe <mark>1000<\/mark> fl zu Completirung des Ubrigen hat eben dieselbe das...","fid":"d24e1790"},{"form":"1000","weight":"1","pos":1040,"context":"...errichteten Heurathsbrief eingelegt, worinnen Heurathguth 500 fl Widerlaag <mark>1000<\/mark> fl was jeder theil derzeit eigenthumlich besizet, jedem...","fid":"d24e2132"}]},{"docId":"wkfm-650395","docUri":"wkfm-650395.html","score":2,"contexts":[{"form":"1000","weight":"1","pos":362,"context":"...in Copia vidimata No 2256 eingeleget, krafft welchen <mark>1000<\/mark> fl Heurathsgutt nebst 2000 fl Widerlag und der Handlungsfreyheit...","fid":"d27e910"},{"form":"1000","weight":"1","pos":587,"context":"...Heurath Contract eingelegt, worinnen Heurathsguth 500 fl Widerlaag <mark>1000<\/mark> fl Paraphenum 500 et 200 fl dann zu einer...","fid":"d27e1297"}]},{"docId":"wkfm-650360","docUri":"wkfm-650360.html","score":1,"contexts":[{"form":"1000","weight":"1","pos":428,"context":"...orig: eingeleget, worinn er Heurathsguth 500 Widerlag <mark>1000<\/mark> und Morgengab von dem Brauthigam der Brauth 300 fl....","fid":"d21e1022"}]}]}