{"stem":"142","instances":[{"docId":"560230","docUri":"560230.html","score":6,"contexts":[{"form":"142","weight":"2","pos":5332,"context":"Seite <mark>142<\/mark>","fid":"page"},{"form":"142","weight":"1","pos":10751,"context":"...Guiseppe Batuzzi laut Erklährung sine dato N o No <mark>142<\/mark> den 20ten Decembris 1763 hat sine firma und...","fid":"page"},{"form":"142","weight":"1","pos":10760,"context":"...Decembris 1763 hat sine firma und Erklärung eingeleget nro <mark>142<\/mark> 1\/2    Der Joseph Batuzzi hat zu Ausweisung seines fundi...","fid":"page"},{"form":"142","weight":"1","pos":10833,"context":"...1\/8 Teil tl Gewinn associret habe. Vide firma nro <mark>142<\/mark> 1\/2  Anmerckungen","fid":"page"},{"form":"142","weight":"1","pos":10839,"context":" <mark>142<\/mark>  Plankh Johann Niclas burgerlicher Handlsmann  Johann Nicolaus Plankh laut...","fid":"page"}]},{"docId":"650362","docUri":"650362.html","score":3,"contexts":[{"form":"142","weight":"2","pos":4333,"context":"Seite <mark>142<\/mark>","fid":"page"},{"form":"142","weight":"1","pos":9804,"context":" <mark>142<\/mark> 840  Schreiber Anton Thomas burgerlicher Handlsmann  Anton Thomas Schreiberl...","fid":"page"}]},{"docId":"560252","docUri":"560252.html","score":2,"contexts":[{"form":"142","weight":"2","pos":5388,"context":"Seite <mark>142<\/mark>","fid":"page"}]},{"docId":"650348","docUri":"650348.html","score":2,"contexts":[{"form":"142","weight":"2","pos":6753,"context":"Seite <mark>142<\/mark>","fid":"page"}]},{"docId":"560296","docUri":"560296.html","score":2,"contexts":[{"form":"142","weight":"2","pos":6203,"context":"Seite <mark>142<\/mark>","fid":"page"}]}]}