{"stem":"153","instances":[{"docId":"wkfm-560230","docUri":"wkfm-560230.html","score":3,"contexts":[{"form":"153","weight":"1","pos":5949,"context":"<mark>153<\/mark>","fid":"page"},{"form":"153","weight":"1","pos":12037,"context":"...Frantz Joseph Bergh Bargehr laut Erklährung sine dato No <mark>153<\/mark> welche derselbe mitls Anbringen de ps: 25ten 7br:...","fid":"d10e22176"},{"form":"153","weight":"1","pos":12634,"context":" <mark>153<\/mark> Nahmen und Class Bader Emerich Felix k. k. Niderlags...","fid":"d10e23248"}]},{"docId":"wkfm-560252","docUri":"wkfm-560252.html","score":1,"contexts":[{"form":"153","weight":"1","pos":5840,"context":"<mark>153<\/mark>","fid":"page"}]},{"docId":"wkfm-650395","docUri":"wkfm-650395.html","score":1,"contexts":[{"form":"153","weight":"1","pos":9,"context":" <mark>153<\/mark> 890 908 Nahmen und Class Zacher Johann burgerlicher Handlsmann...","fid":"d27e315"}]},{"docId":"wkfm-650362","docUri":"wkfm-650362.html","score":1,"contexts":[{"form":"153","weight":"1","pos":4633,"context":"<mark>153<\/mark>","fid":"page"}]}]}