{"stem":"1800","instances":[{"docId":"wkfm-560252","docUri":"wkfm-560252.html","score":2,"contexts":[{"form":"1800","weight":"1","pos":5332,"context":"...: pr 420 fl Einen Wechselbrief von  Cecotti  pr <mark>1800<\/mark> fl Einen det: von  Radlio  pr 1200 fl...","fid":"d6e10775"},{"form":"1800","weight":"1","pos":6675,"context":"...Vermögen sowohl als jenes seiner Ehewirthin an Vätterlichen pr <mark>1800<\/mark> fl und mütterlicher Geschanknus pr 1200 fl ohne Zühung...","fid":"d6e13126"}]},{"docId":"wkfm-650350","docUri":"wkfm-650350.html","score":1,"contexts":[{"form":"1800","weight":"1","pos":2765,"context":"...No 1590 an 300 Emmer Wein à 6 fl <mark>1800<\/mark> fl an baaren Geld 600 fl zusamen Eigenthum 3000...","fid":"d13e5227"}]},{"docId":"wkfm-560296","docUri":"wkfm-560296.html","score":1,"contexts":[{"form":"1800","weight":"1","pos":4267,"context":"...1438 habe ihre selbe zur Sicherheit deren Creditoren uberlossen <mark>1800<\/mark> fl Zusamen Eigenthum 2600 fl Zu Completirung des übrigen...","fid":"d9e8540"}]},{"docId":"wkfm-650384","docUri":"wkfm-650384.html","score":1,"contexts":[{"form":"1800","weight":"1","pos":3935,"context":"...16ten Mart: 754 No 18127 eingeleget pr <mark>1800<\/mark> fl Sa 4000 fl","fid":"d20e7626"}]},{"docId":"wkfm-650362","docUri":"wkfm-650362.html","score":1,"contexts":[{"form":"1800","weight":"1","pos":7557,"context":"...2300 fl bey Johann Michäl Mayr in zweyen Posten <mark>1800<\/mark> fl bey Batthot: Akherl in Gräz 616 fl...","fid":"d18e13982"}]}]}