{"stem":"295","instances":[{"docId":"wkfm-560280","docUri":"wkfm-560280.html","score":2,"contexts":[{"form":"295","weight":"1","pos":129,"context":"...Hieronimus burgerlicher Handlsmann  Hieronymus Eberl laut Erklährung dd too <mark>295<\/mark>.    ","fid":"d13e715"},{"form":"295","weight":"1","pos":145,"context":"  Im obigener d Erklährung sine dato No <mark>295<\/mark> hat sich der Eberl geäussert daß er gahr keinen...","fid":"d13e750"}]},{"docId":"wkfm-560275","docUri":"wkfm-560275.html","score":2,"contexts":[{"form":"295","weight":"1","pos":3549,"context":" <mark>295<\/mark>  Träge Johann Sebastian burgerlicher Handlsmann  Johann Sebastian Träge laut...","fid":"d12e7164"},{"form":"295","weight":"1","pos":4270,"context":"...mitls anbringen de ps: 15ten Julii 754 No <mark>295<\/mark> eingeleget    Der Tschofen hat seinen Fundum folgender maßen mitls...","fid":"d12e8253"}]}]}