{"stem":"536","instances":[{"docId":"wkfm-650350","docUri":"wkfm-650350.html","score":1,"contexts":[{"form":"536","weight":"1","pos":2239,"context":"...ad Raggion Frantz Lazarus laut Erklährung sine dato No <mark>536<\/mark> Procura und Firmae Trager Oblatorien und Avocatorien Fundi Ausweisung...","fid":"d18e4500"}]},{"docId":"wkfm-650377","docUri":"wkfm-650377.html","score":1,"contexts":[{"form":"536","weight":"1","pos":707,"context":" <mark>536<\/mark> Nahmen und Class Ipditsch Franz Anton burgerlicher Tuchlaubens Verwanter...","fid":"d24e1672"}]}]}