{"stem":"549","instances":[{"docId":"wkfm-650350","docUri":"wkfm-650350.html","score":3,"contexts":[{"form":"549","weight":"2","pos":19,"context":"Wiener Merkantilprotokoll 11 Lit L fol 544 [<mark>549<\/mark>]-585 [590]","fid":"page"},{"form":"549","weight":"1","pos":647,"context":" <mark>549<\/mark>  Leeb Paul seel: Wittib burgerliche Tuchlaubens Verwante  Paul...","fid":"d13e1765"}]},{"docId":"wkfm-650351","docUri":"wkfm-650351.html","score":2,"contexts":[{"form":"549","weight":"1","pos":468,"context":"...Anbringen de ps: 26ten Apr: 725 No <mark>549<\/mark>    ","fid":"d14e1747"},{"form":"549","weight":"1","pos":485,"context":"...Anbringen de ps: 26ten Apr: 725 No <mark>549<\/mark> hat sich der Mobré erklähret, das er seine...","fid":"d14e1801"}]},{"docId":"toc","docUri":"toc.html","score":1,"contexts":[{"form":"549","weight":"1","pos":57,"context":"Wiener Merkantilprotokoll 11 Lit L fol 544 [<mark>549<\/mark>]-585 [590]","fid":"tocTable"}]}]}