{"stem":"776","instances":[{"docId":"650362","docUri":"650362.html","score":4,"contexts":[{"form":"776","weight":"1","pos":3169,"context":" 131 <mark>776<\/mark>  De Sorbait Paul burgerlicher Handlsmann  Paul De Sorbait laut...","fid":"page"},{"form":"776","weight":"1","pos":5332,"context":"...Anmerckungen Vermög Anbringen de psto: 25ten Julij <mark>776<\/mark> haben die Gebrüder Smittmer ange- zeiget, daß...","fid":"page"},{"form":"776","weight":"1","pos":9099,"context":"...Handlsmann  Franz Carl Sotscheckh laut Erklährung sine dato No <mark>776<\/mark> welche derselbe mitls Anbringen de ps: 11ten Julii...","fid":"page"},{"form":"776","weight":"1","pos":10456,"context":"...Anmerckungen Vermög Hof Decret de psto 5 Aug: <mark>776<\/mark> ist auf Anlangen der hiesigen Banquiers Jakob und Michael...","fid":"page"}]},{"docId":"560230","docUri":"560230.html","score":2,"contexts":[{"form":"776","weight":"1","pos":10020,"context":"...Anmerckungen Vermög Anbringen de psto: 14ten 8b: <mark>776<\/mark> hat die Franz Beda seel. Wittib ange zeiget...","fid":"page"},{"form":"776","weight":"1","pos":10047,"context":"...: Worüber der bericht de psto: 25: 8br: <mark>776<\/mark> von hierorts erstattet an Regierung erstattet worden und lieget...","fid":"page"}]}]}