{"stem":"activa","instances":[{"docId":"wkfm-650348","docUri":"wkfm-650348.html","score":3,"contexts":[{"form":"activa","weight":"1","pos":449,"context":"...fl hinaus bezahlet, und die Handlung mit allein <mark>activa<\/mark> und Passiva Schulden und am mit gänzlicher Loß-...","fid":"d17e1902"},{"form":"activa","weight":"1","pos":1380,"context":"...- stehlet, daß sie mit Schadloßhaltung seiner alle <mark>activa<\/mark> und Passiva so unter der raggion Joseph Hökhsteiner biß...","fid":"d17e3527"},{"form":"activa","weight":"1","pos":3934,"context":"...aber und Falkh aber alle Rad und Hößlin: <mark>activa<\/mark> und Passiva auf sich genohmen und entschlossen haben dieses...","fid":"d17e7822"}]},{"docId":"wkfm-560230","docUri":"wkfm-560230.html","score":1,"contexts":[{"form":"activa","weight":"1","pos":8711,"context":"...1188 pr 33 33847 fl 7 xr Übermaß in <mark>activa<\/mark> zu folge der Verwilligung ddto 28ten Jan:...","fid":"d10e16674"}]},{"docId":"wkfm-650361","docUri":"wkfm-650361.html","score":1,"contexts":[{"form":"activa","weight":"1","pos":166,"context":"...Hößlin und Falkh aber alle Rad und Hößlin: <mark>activa<\/mark> und passiva auf sich genohmen und entschlossen haben, dieses...","fid":"d22e1120"}]},{"docId":"wkfm-650351","docUri":"wkfm-650351.html","score":1,"contexts":[{"form":"activa","weight":"1","pos":3675,"context":"...das er möglichst beflissen sein werde, die Wohlgemuth: <mark>activa<\/mark> einzubringen und mit die Wohlgemuth: Creditores nach denen...","fid":"d19e6923"}]}]}