{"stem":"beeydiget","instances":[{"docId":"650354","docUri":"650354.html","score":1,"contexts":[{"form":"beeydiget","weight":"1","pos":1080,"context":"...laut beygerukter formula jurandi untern 14ten 9br: 748 <mark>beeydiget<\/mark>, folgender maßen ausgewisen, nemlich das er eigenthumlich...","fid":"d15e2737"}]},{"docId":"650361","docUri":"650361.html","score":1,"contexts":[{"form":"beeydiget","weight":"1","pos":3741,"context":"...1675, welche derselbe untern 26ten Junii 747 <mark>beeydiget<\/mark> folgendermaßen ausgewisen, nemlich daß er eigenthumlich besize an...","fid":"d17e9628"}]},{"docId":"650362","docUri":"650362.html","score":1,"contexts":[{"form":"beeydiget","weight":"1","pos":10308,"context":"...Post hat der Schekenberger laut Formula jurandi No 1799 <mark>beeydiget<\/mark> zusamen Eigenthum 3115 fl zu Completirung des übrigen hat...","fid":"d18e23510"}]}]}