{"stem":"dußel","instances":[{"docId":"wkfm-560275","docUri":"wkfm-560275.html","score":5,"contexts":[{"form":"Dußell","weight":"1","pos":814,"context":" 263 Nahmen und Class <mark>Dußell<\/mark> Johann Georg burgerlicher Handlsmann Firma ad Raggion Johann Georg...","fid":"d12e2597"},{"form":"Dußell","weight":"1","pos":849,"context":"...ten Apr: 725 No 257 hat sich der <mark>Dußell<\/mark> geäusseret, daß er keine Compagnia noch Verständ-...","fid":"d12e2641"},{"form":"Dußel","weight":"1","pos":1713,"context":" 279 Nahmen und Class <mark>Dußel<\/mark> Johann Dominicus burgerlicher Handlsmann Firma ad Raggion Johann Dommini...","fid":"d12e4238"},{"form":"Dußel","weight":"1","pos":1723,"context":"...Dominicus burgerlicher Handlsmann Firma ad Raggion Johann Dommini Dominico <mark>Dußel<\/mark> laut Erklährung ddto 16ten Janu: 727 No...","fid":"d12e4238"},{"form":"Dußel","weight":"1","pos":1749,"context":"...ten Janu: 727 No 272 hat sich der <mark>Dußel<\/mark> geäusseret, daß er keinen Compagnon habe Heuraths Contract...","fid":"d12e4291"}]}]}