{"stem":"egidi","instances":[{"docId":"wkfm-560230","docUri":"wkfm-560230.html","score":2,"contexts":[{"form":"Egidi","weight":"1","pos":4212,"context":" 82  Päkh <mark>Egidi<\/mark> Philipp burgerlicher Handlsmann Firma oder Raggion Egidi Philiph Päkh...","fid":"d10e9983"},{"form":"Egidi","weight":"1","pos":4218,"context":"...82  Päkh Egidi Philipp burgerlicher Handlsmann Firma oder Raggion <mark>Egidi<\/mark> Philiph Päkh laut Erklährung ddto 2ten Mart:...","fid":"d10e9983"}]},{"docId":"wkfm-650362","docUri":"wkfm-650362.html","score":1,"contexts":[{"form":"Egidi","weight":"1","pos":2446,"context":" 761  Schuester Johann Egidius burgerlicher Handlsmann  Johann <mark>Egidi<\/mark> Schuester laut Erklährung ddto 17ten Apr: 725...","fid":"d23e6228"}]}]}