{"stem":"erklaret","instances":[{"docId":"wkfm-560230","docUri":"wkfm-560230.html","score":1,"contexts":[{"form":"erklaret","weight":"1","pos":12152,"context":"...ten Xbris 763 hat sich der Franz Joseph Bargehr <mark>erklaret<\/mark>, das er seinen Bruder Johann Benedict Bargehr und...","fid":"d10e22408"}]},{"docId":"wkfm-650362","docUri":"wkfm-650362.html","score":1,"contexts":[{"form":"erklaret","weight":"1","pos":10234,"context":"...Georg Scheckenberger mittels Einlegung seiner firma nro: 792 <mark>erklaret<\/mark>, das er seinen Handlungs Bedienten Franz  Joseph Plazer...","fid":"d23e18250"}]}]}