{"stem":"grässl","instances":[{"docId":"wkfm-564767","docUri":"wkfm-564767.html","score":3,"contexts":[{"form":"Grässl","weight":"1","pos":1647,"context":" 434 Nahmen und Class <mark>Grässl<\/mark> Frantz Anton burgerlicher Handlsmann Firma ad Raggion Frantz Antonj...","fid":"d15e3970"},{"form":"Grässl","weight":"1","pos":1656,"context":"...Frantz Anton burgerlicher Handlsmann Firma ad Raggion Frantz Antonj <mark>Grässl<\/mark> laut Erklährung ddto 15ten 7br: 729 No 410...","fid":"d15e3970"},{"form":"Grässl","weight":"1","pos":1680,"context":"...15ten 7br: 729 No 410 hat sich der <mark>Grässl<\/mark> geäusseret, daß er seine Handlung ohne Compagnon führe...","fid":"d15e4016"}]}]}