{"stem":"himmelberg","instances":[{"docId":"wkfm-650348","docUri":"wkfm-650348.html","score":3,"contexts":[{"form":"Himmelberger","weight":"1","pos":2852,"context":" 492 Nahmen und Class <mark>Himmelberger<\/mark> Johann Adam burgerlicher Handlsmann Firma ad Raggion Johann Adam...","fid":"d17e6069"},{"form":"Himmelberger","weight":"1","pos":2861,"context":"...Johann Adam burgerlicher Handlsmann Firma ad Raggion Johann Adam <mark>Himmelberger<\/mark> laut Erklährung ddto 17ten Aug: 728 No...","fid":"d17e6069"},{"form":"Himmelberger","weight":"1","pos":2887,"context":"...ten Aug: 728 No 461 hat sich der <mark>Himmelberger<\/mark> geäusseret, daß er seine Handlung allein führe Heuraths...","fid":"d17e6116"}]}]}