{"stem":"kraschinkh","instances":[{"docId":"wkfm-560252","docUri":"wkfm-560252.html","score":2,"contexts":[{"form":"Kraschinkh","weight":"1","pos":6333,"context":" 239 Nahmen und Class <mark>Kraschinkh<\/mark> Joseph burgerlicher Handlsmann Firma ad Raggion Joseph Kraschinkh laut...","fid":"d11e12632"},{"form":"Kraschinkh","weight":"1","pos":6340,"context":"...Class Kraschinkh Joseph burgerlicher Handlsmann Firma ad Raggion Joseph <mark>Kraschinkh<\/mark> laut Erklährung ddto 28ten 8br: 753 No 235...","fid":"d11e12632"}]}]}