{"stem":"müllnitsch","instances":[{"docId":"wkfm-650351","docUri":"wkfm-650351.html","score":4,"contexts":[{"form":"Müllnitsch","weight":"1","pos":259,"context":" 590  <mark>Müllnitsch<\/mark> Veith hofbefreyter Tuchhandler  Veith Müllnitsch laut Anbringen de ps:...","fid":"d19e1416"},{"form":"Müllnitsch","weight":"1","pos":266,"context":" 590  Müllnitsch Veith hofbefreyter Tuchhandler  Veith <mark>Müllnitsch<\/mark> laut Anbringen de ps: 19ten Apr: 725...","fid":"d19e1416"},{"form":"Müllnitsch","weight":"1","pos":3480,"context":" 632  <mark>Müllnitsch<\/mark> Veith Anton burgerlicher Tuchlauben Verwanter     ","fid":"d19e6844"},{"form":"Müllnitsch","weight":"1","pos":3507,"context":"...ps: 14ten Junii 745 No 2198 hat der <mark>Müllnitsch<\/mark> den mit der Maria Anna TheresiaWinklerin untern 5ten...","fid":"d19e6867"}]}]}