{"stem":"orban","instances":[{"docId":"wkfm-650360","docUri":"wkfm-650360.html","score":3,"contexts":[{"form":"Orban","weight":"1","pos":334,"context":" 663  <mark>Orban<\/mark> Johann Sebastian burgerlicher Handlsmann  Johann Sebastian Orban laut Anbringen...","fid":"d21e888"},{"form":"Orban","weight":"1","pos":343,"context":" 663  Orban Johann Sebastian burgerlicher Handlsmann  Johann Sebastian <mark>Orban<\/mark> laut Anbringen Erklährung ddto 23ten Mart: 733...","fid":"d21e888"},{"form":"Orban","weight":"1","pos":370,"context":"...ten Mart: 722 No 614 hat sich der <mark>Orban<\/mark> geäusseret, daß er seine Handlung ohne Compagnon führe...","fid":"d21e936"}]}]}