{"stem":"passi","instances":[{"docId":"wkfm-560230","docUri":"wkfm-560230.html","score":32,"contexts":[{"form":"Passy","weight":"1","pos":8504,"context":" 123  <mark>Passy<\/mark> Michael k. k. Niderlags Verwanter  Michäel Passy laut anbringen...","fid":"d10e16674"},{"form":"Passy","weight":"1","pos":8511,"context":" 123  Passy Michael k. k. Niderlags Verwanter  Michäel <mark>Passy<\/mark> laut anbringen de ps: 13ten 8br: 738 No...","fid":"d10e16674"},{"form":"Passy","weight":"1","pos":8517,"context":"...anbringen de ps: 13ten 8br: 738 No 122 <mark>Passy<\/mark> et Perinet laut Anbringen de ps: 23ten Mart...","fid":"d10e16674"},{"form":"Passy","weight":"1","pos":8531,"context":"...oblatorien ddto 2ten Febr: 750 No 1101 <mark>Passy<\/mark> Perinet et Comp: laut Anbringen de ps: 8...","fid":"d10e16674"},{"form":"Passy","weight":"1","pos":8558,"context":"...sub nro: 166  In dem von der Raggion <mark>Passy<\/mark> und Perinet untern 2ten Febr: 750 No...","fid":"d10e16674"},{"form":"Passy","weight":"1","pos":8580,"context":"...Aug: 754 No 1887 ist von der Raggion <mark>Passy<\/mark> Perinetet Comp:  die Firma allein von Michael Passy...","fid":"d10e16674"},{"form":"Passy","weight":"1","pos":8585,"context":"...Passy Perinetet Comp:  die Firma allein von Michael <mark>Passy<\/mark> und Philibert Anton Perinet einge- leget worden.  Die...","fid":"d10e16674"},{"form":"Passy","weight":"1","pos":8594,"context":"...Philibert Anton Perinet einge- leget worden.  Die Raggion <mark>Passy<\/mark> und Perinet hat die oblatorien untern 2ten Febr...","fid":"d10e16674"},{"form":"Passy","weight":"1","pos":8608,"context":"...subsistirende societaet unter der Raggion in Augspurg Perinet und <mark>Passy<\/mark> und allein Michäl Passy mit ende vorigen Jahrs ter...","fid":"d10e16674"},{"form":"Passy","weight":"1","pos":8610,"context":"...Raggion in Augspurg Perinet und Passy und allein Michäl <mark>Passy<\/mark> mit ende vorigen Jahrs ter- miniret seye,...","fid":"d10e16674"},{"form":"Passy","weight":"1","pos":8617,"context":"...vorigen Jahrs ter- miniret seye, der Michäl <mark>Passy<\/mark> habe sich aber entschlossen, die societaet mit dem...","fid":"d10e16674"},{"form":"Passy","weight":"1","pos":8627,"context":"...bert Perinet mit genugsamen Fundi und unter der Raggion <mark>Passy<\/mark> und Perinet, wie vorhero zu continuiren Die Raggion...","fid":"d10e16674"},{"form":"Passy","weight":"1","pos":8632,"context":"...und Perinet, wie vorhero zu continuiren Die Raggion <mark>Passy<\/mark> Perinet und Comp hat die weithern oblatorien untern 5...","fid":"d10e16674"},{"form":"Passy","weight":"1","pos":8645,"context":"...1107 dahin erlassen, das der Peter und Franz <mark>Passy<\/mark> in das negotium associret und die Raggion auf Passy...","fid":"d10e16674"},{"form":"Passy","weight":"1","pos":8649,"context":"...Passy in das negotium associret und die Raggion auf <mark>Passy<\/mark> Perinet und Comp:  abgeändert worden seye.  Der...","fid":"d10e16674"},{"form":"Passy","weight":"1","pos":8657,"context":"...und Comp:  abgeändert worden seye.  Der Michäl <mark>Passy<\/mark> hat seinen fundum mitls dreyer von FranzDecret, Bernhard...","fid":"d10e16674"},{"form":"Passy","weight":"1","pos":8684,"context":"...bezeigen, daß ihn wissend seye, daß der <mark>Passy<\/mark> an eignen Mitlen 20000 fl besize, dann einen...","fid":"d10e16674"},{"form":"Passy","weight":"1","pos":8696,"context":"...- tions Instrument, welches über die von dem <mark>Passy<\/mark> eingelegte Inven- tur ddto 31ten Janu:...","fid":"d10e16674"},{"form":"Passy","weight":"1","pos":8723,"context":"...beygerukter Quittung ddto 30ten ej: No 1186 dem <mark>Passy<\/mark> extradiret worden.","fid":"d10e16674"},{"form":"Passy","weight":"1","pos":8735,"context":"...13ten 8br: 738 No 122 hat sich der <mark>Passy<\/mark> erklähret, daß er sein Negotium unter seinem alleinigen...","fid":"d10e17066"},{"form":"Passy","weight":"1","pos":8748,"context":"...23ten Mart: 744 No 1881 hat Michäl <mark>Passy<\/mark> und Philibert Perinet sich erklähret, daß sie zusamen...","fid":"d10e17066"},{"form":"Passy","weight":"1","pos":8774,"context":"...die Societaet auf 6 Jahr und die Raggion auf <mark>Passy<\/mark> etPerinet stabiliret worden, der Passy 35000 fl und der...","fid":"d10e17066"},{"form":"Passy","weight":"1","pos":8777,"context":"...und die Raggion auf Passy etPerinet stabiliret worden, der <mark>Passy<\/mark> 35000 fl und der Perinet 17000 fl einge-...","fid":"d10e17066"},{"form":"Passy","weight":"1","pos":8806,"context":"...ps: 8ten Aug: 754 No 1887 hat <mark>Passy<\/mark> und Perinet angezeiget, daß sie ihr ihrer Handlung...","fid":"d10e17066"},{"form":"Passy","weight":"1","pos":8812,"context":"...daß sie ihr ihrer Handlung der Peter und Franz <mark>Passy<\/mark> ohne jedoch ohne ihre Risico und obligo associret haben....","fid":"d10e17066"},{"form":"Passy","weight":"1","pos":8826,"context":"...Anno 764 die Societät angez neuerdings angezeiget zwischen Michäl <mark>Passy<\/mark> 0 Philibert Anton Perinet, Peter Bassy und Franz...","fid":"d10e17066"},{"form":"Passy","weight":"1","pos":8859,"context":"...Comp:  angezeiget, das ihr gewester associe Franz  <mark>Passy<\/mark> verblieben seyen. In societäts Cont: nro 1887...","fid":"d10e17066"},{"form":"Passy","weight":"1","pos":10939,"context":" 143  <mark>Passy<\/mark> Georg k. k. Niderlags Verwanter  Georg Passy laut Anbringen...","fid":"d10e20594"},{"form":"Passy","weight":"1","pos":10946,"context":" 143  Passy Georg k. k. Niderlags Verwanter  Georg <mark>Passy<\/mark> laut Anbringen de ps: 26ten Jun: 747...","fid":"d10e20594"},{"form":"Passy","weight":"1","pos":10961,"context":"...26ten Jun: 747 No 144    Der Georg <mark>Passy<\/mark> hat seinen fundum mitls einer orig: nota sine...","fid":"d10e20594"},{"form":"Passy","weight":"1","pos":11039,"context":"...ten Aug: 754 No 2114 hat der Georg <mark>Passy<\/mark> der mit der Anna Theresia Orsetin untern 10ten...","fid":"d10e20752"},{"form":"Passy","weight":"1","pos":12117,"context":"...zwei orig: Cautions Instrumenta, alß von Michäl <mark>Passy<\/mark> ddto 4ten Aug: 753 No 1253 2000...","fid":"d10e22176"}]},{"docId":"wkfm-560252","docUri":"wkfm-560252.html","score":4,"contexts":[{"form":"Passy","weight":"1","pos":4543,"context":"...742 No 1909 dann eine Erklährung von Puthon, <mark>Passy<\/mark>, Perinet und Violand, Gebrüder Ducret les freres...","fid":"d11e9464"},{"form":"Passy","weight":"1","pos":4552,"context":"..., Gebrüder Ducret les freres Crettier, Ruard et <mark>Passy<\/mark>, Bedal und Pellisier, daß sie als Condray...","fid":"d11e9464"},{"form":"Passy","weight":"1","pos":4659,"context":"...742 No 1909 dann eine Erklährung von Buthon, <mark>Passy<\/mark>, Perinet und Violland Gebrüder Decret, les Freres...","fid":"d11e9651"},{"form":"Passy","weight":"1","pos":4668,"context":"...Gebrüder Decret, les Freres Crettier, Ruard und <mark>Passy<\/mark> Bedal und Belissier, daß sie als Condray Handlungs...","fid":"d11e9651"}]}]}