{"stem":"pernätzschki","instances":[{"docId":"wkfm-560230","docUri":"wkfm-560230.html","score":2,"contexts":[{"form":"Pernätzschky","weight":"1","pos":10221,"context":"...Pernätschky Anton burg: Handlsmann Firma ad Raggion Anton <mark>Pernätzschky<\/mark> laut Erklährung ddto 18ten Mart: 743 No...","fid":"d10e19374"},{"form":"Pernätzschky","weight":"1","pos":10236,"context":"...und Firmae Trager Oblatorien und Avocatorien Fundi Ausweisung Der <mark>Pernätzschky<\/mark> hat zu Ausweisung seines Fundi ein von seiner Ehe...","fid":"d10e19374"}]}]}