{"stem":"pfitzenreit","instances":[{"docId":"560230","docUri":"560230.html","score":3,"contexts":[{"form":"Pfitzenreiter","weight":"1","pos":4514,"context":" 86  <mark>Pfitzenreiter<\/mark> Johann Christoph burgerlicher Handlsmann  Johann Christoph Pfitzenreiter laut Erklährung...","fid":"d5e16841"},{"form":"Pfitzenreiter","weight":"1","pos":4523,"context":" 86  Pfitzenreiter Johann Christoph burgerlicher Handlsmann  Johann Christoph <mark>Pfitzenreiter<\/mark> laut Erklährung ddto: 29ten Jul: 727...","fid":"d5e16841"},{"form":"Pfitzenreiter","weight":"1","pos":4548,"context":"...ten Jul: 829 No 81 hat sich der <mark>Pfitzenreiter<\/mark> geäusseret, das er keinen Compagnon habe.   ","fid":"d5e16885"}]}]}