{"stem":"pingiz","instances":[{"docId":"560230","docUri":"560230.html","score":5,"contexts":[{"form":"Pingizer","weight":"1","pos":5734,"context":" 97  <mark>Pingizer<\/mark> Pingizer et Pittoni junior burgerliche Handlsleuth  Pingizer et Pittonj...","fid":"page"},{"form":"Pingizer","weight":"1","pos":5735,"context":" 97  Pingizer <mark>Pingizer<\/mark> et Pittoni junior burgerliche Handlsleuth  Pingizer et Pittonj Junior...","fid":"page"},{"form":"Pingizer","weight":"1","pos":5742,"context":" 97  Pingizer Pingizer et Pittoni junior burgerliche Handlsleuth  <mark>Pingizer<\/mark> et Pittonj Junior laut Erklährung ddto 26ten Mart...","fid":"page"},{"form":"Pingizer","weight":"1","pos":5782,"context":"...26ten Mart: 733 No 1860 hat sich <mark>Pingizer<\/mark>  et Pittonj junior angetretten haben und prosequiren werden.  Mitls...","fid":"page"},{"form":"Pingizer","weight":"1","pos":5795,"context":"...5ten 7br: 737 No 2084 hat der Joseph <mark>Pingizer<\/mark> der mit der Maria Josepha Kauthsamberin untern 20ten...","fid":"page"}]}]}