{"stem":"pittonj","instances":[{"docId":"wkfm-560230","docUri":"wkfm-560230.html","score":2,"contexts":[{"form":"Pittonj","weight":"1","pos":5720,"context":"...Pittoni junior burgerliche Handlsleuth Firma oder Raggion Pingizer et <mark>Pittonj<\/mark> Junior laut Erklährung ddto 26ten Mart: 733...","fid":"d10e12520"},{"form":"Pittonj","weight":"1","pos":5760,"context":"...Mart: 733 No 1860 hat sich Pingizer  et <mark>Pittonj<\/mark> junior angetretten haben und prosequiren werden. Heuraths Contract Mitls...","fid":"d10e12589"}]}]}