{"stem":"purckholz","instances":[{"docId":"wkfm-560230","docUri":"wkfm-560230.html","score":2,"contexts":[{"form":"Purckholzer","weight":"1","pos":5962,"context":"...Christian Johann burgerlicher Handlsmann Firma oder Raggion Christian Johann <mark>Purckholzer<\/mark> laut Erklährung ddto 28ten Mart: 733 No...","fid":"d10e12936"},{"form":"Purckholzer","weight":"1","pos":5994,"context":"...ten Mart: 733 No 94 hat sich der <mark>Purckholzer<\/mark> geäusseret, das er seine Handlung für sich allein...","fid":"d10e12996"}]}]}