{"stem":"schenöckher","instances":[{"docId":"wkfm-650362","docUri":"wkfm-650362.html","score":2,"contexts":[{"form":"Schenöckher","weight":"1","pos":9940,"context":" 841  <mark>Schenöckher<\/mark> Johann Michäl burgerlicher Handlsmann  Ao: 763 hat der Johann...","fid":"d23e17841"},{"form":"Schenöckher","weight":"1","pos":9966,"context":"...daß er keinen Compagnon in seiner Handlung habe    Der <mark>Schenöckher<\/mark> hat mit seinen Fundum mitls der Specification No 1787...","fid":"d23e17841"}]}]}