{"stem":"vidimirt","instances":[{"docId":"wkfm-650384","docUri":"wkfm-650384.html","score":1,"contexts":[{"form":"vidimirter","weight":"1","pos":1072,"context":"...und Sohn ist zu ausweisung des handlungs Fundi ein <mark>vidimirter<\/mark> Extract aus der Johann Wagner seinen untern 3  ten...","fid":"d25e2918"}]},{"docId":"wkfm-560252","docUri":"wkfm-560252.html","score":1,"contexts":[{"form":"vidimirte","weight":"1","pos":4386,"context":"...Xbr: 739 dem Klebinger erfolget und hingegen die <mark>vidimirte<\/mark> abschrifft vom selben No 2120 eingeleget worden. Anmerckungen","fid":"d11e9226"}]}]}