{"stem":"winkhlerin","instances":[{"docId":"wkfm-650384","docUri":"wkfm-650384.html","score":3,"contexts":[{"form":"Winkhlerin","weight":"1","pos":733,"context":" 855  <mark>Winkhlerin<\/mark> vorhin Sprintzlin Jacobina burg kay: könig: Niderlags...","fid":"d25e2422"},{"form":"Winkhlerin","weight":"1","pos":745,"context":"...Jacobina burg kay: könig: Niderlags Verwante  Jacobina <mark>Winkhlerin<\/mark> vorhin Sprintzlin Wittib laut Anbringen de ps: 8ten...","fid":"d25e2422"},{"form":"Winkhlerin","weight":"1","pos":772,"context":"...8ten Junii 725 No 792 hat sich die <mark>Winkhlerin<\/mark>  vorhin Sprintzlin  Marx Sprintzl und nunmehro ihren Nahmen laufenden...","fid":"d25e2460"}]}]}