{"stem":"winterl","instances":[{"docId":"650384","docUri":"650384.html","score":3,"contexts":[{"form":"Winterl","weight":"1","pos":1994,"context":" 878 148  <mark>Winterl<\/mark> Johann Joseph burgerlicher Handlsmann  Johann Joseph Winterl laut Erklährung...","fid":"page"},{"form":"Winterl","weight":"1","pos":2003,"context":"...878 148  Winterl Johann Joseph burgerlicher Handlsmann  Johann Joseph <mark>Winterl<\/mark> laut Erklährung ddto 9ten Junii 728 No 813...","fid":"page"},{"form":"Winterl","weight":"1","pos":2029,"context":"...9ten Junii 728 No 813 hat sich der  <mark>Winterl<\/mark>  geäusseret, daß er seine Handlung ohne Comp:...","fid":"page"}]}]}